LICENSE
README.md
setup.py
tests/test_auth.py
tests/test_base_func.py
tests/test_bucket.py
tests/test_checkpoint.py
tests/test_control.py
tests/test_list_objects.py
tests/test_multipart.py
tests/test_object.py
tests/test_v2_bucket.py
tests/test_v2_crc.py
tests/test_v2_encryption.py
tests/test_v2_multipart.py
tests/test_v2_object.py
tests/test_v2_with_version.py
tos/__init__.py
tos/__version__.py
tos/auth.py
tos/checkpoint.py
tos/client.py
tos/clientv2.py
tos/consts.py
tos/convertor.py
tos/credential.py
tos/enum.py
tos/exceptions.py
tos/http.py
tos/json_utils.py
tos/log.py
tos/mine_type.py
tos/models.py
tos/models2.py
tos/safe_map.py
tos/thread_ctx.py
tos/utils.py
tos.egg-info/PKG-INFO
tos.egg-info/SOURCES.txt
tos.egg-info/dependency_links.txt
tos.egg-info/requires.txt
tos.egg-info/top_level.txt