Metadata-Version: 2.1
Name: tos
Version: 2.8.7
Summary: Volc TOS (Tinder Object Storage) SDK
Home-page: https://www.volcengine.com/
Author: sunyushan
Author-email: sunyushan.jason@bytedance.com
Keywords: boilerplate
Classifier: Intended Audience :: Developers
Classifier: Programming Language :: Python :: 3.5
Classifier: Programming Language :: Python :: 3.6
Classifier: Programming Language :: Python :: 3.7
Classifier: Programming Language :: Python :: 3.8
Classifier: Programming Language :: Python :: 3.9
License-File: LICENSE
